{
  "contents": [
    {
      "id": "8def348848",
      "title": "Googlemapをシンプルかつマーカーがちゃんと表示されるURLで指定するやり方"
    },
    {
      "id": "82a93b152b",
      "title": "[Flutter] iPhone実機へのビルドに失敗した際の解決方法"
    },
    {
      "id": "085bcb597b",
      "title": "AWS AmplifyでReactアプリをデプロイする際に起きたエラー"
    },
    {
      "id": "de0023e398",
      "title": "[Flutter] テキストを揃えたいときの方法3選"
    },
    {
      "id": "1086d35563",
      "title": "スプレッドシートやエクセルのデータをSQLite形式でdbファイルにインポートする手順"
    },
    {
      "id": "421c0a7b6d",
      "title": "[Storybook] Error \"Cannot read property 'displayName' of undefine\""
    },
    {
      "id": "085b2a3887",
      "title": "AWS Elastic Beanstalkで301レスポンスを許可する"
    },
    {
      "id": "fb84a97396",
      "title": "「プログラミング未経験者がWeb/ITエンジニアに転職するためには何をしたらいいのか？」を統計的に分析してみた"
    },
    {
      "id": "5b4afb8d2e",
      "title": "[Flutter]iOSのビルドで失敗したらまず試すこと10選"
    },
    {
      "id": "f8818b67ab",
      "title": "Elastic Beanstalk 環境にDjangoアプリの管理者ユーザーを作成する"
    },
    {
      "id": "fa4ddf29f4",
      "title": "GraphQLのモックAPIがほしい (ApolloServer)"
    },
    {
      "id": "04edd1d773",
      "title": "Docker環境でNext.jsのSSR実装するとき気をつけること"
    },
    {
      "id": "0d6f9709ed",
      "title": "Docker実行時に\"Permission denied\"といわれたらチェックすべき項目5つ"
    },
    {
      "id": "5fbc314fb0",
      "title": "静的WebページをGitHubでホスティングするまでの手順"
    },
    {
      "id": "fb8a0d2da8",
      "title": "SVG奮闘記　ー　SVG要素をぐにょぐにょ動かす実装を完了させるまでに右往左往した話"
    },
    {
      "id": "91a73fd806",
      "title": "[Laravel Sail v11.x, Docker] DBエラーにぶち当たったときに試すこと9選"
    },
    { "id": "d40fbd13d5", "title": "Docker + Fly.ioで爆速デプロイ" },
    { "id": "68e476b5d5", "title": "BEMとSMACSSを融合させる最も簡単な方法" },
    {
      "id": "891d46993a",
      "title": "eslintで任意のディレクトリ、ファイルをチェック対象から除外する方法"
    },
    {
      "id": "a435270b90",
      "title": "Webデザイナーにコーディング力は必要？その理由と重要スキルを解説"
    },
    {
      "id": "560aa3e6e9",
      "title": "【中・上級者向け】外資系企業にITエンジニアが転職内定するための履歴書と職務経歴書の書き方"
    },
    {
      "id": "068814875f",
      "title": "ソフトウェア開発におけるMVPとは？ポートフォリオ作成におけるMVPの役割"
    },
    { "id": "9b19f9ab81", "title": "VBAのIf文入門：基本から実践まで" },
    {
      "id": "06de973bb4",
      "title": "WebスクレイピングをJavaScriptで実現する方法【初心者向け】"
    },
    {
      "id": "841a05fd37",
      "title": "GASで簡単Webスクレイピング！コード例と注意点を解説"
    },
    {
      "id": "e078af3026",
      "title": "Puppeteerの使い方完全マニュアル【スクレイピング・自動化・応用例】"
    },
    {
      "id": "b6cb293891",
      "title": "VBAで始めるWebスクレイピング：初心者向けガイド"
    },
    {
      "id": "9be3da431e",
      "title": "Pythonで始めるデータ分析入門：初心者でもわかるステップバイステップガイド"
    },
    {
      "id": "18d37c950a",
      "title": "Pandasでデータをソートする方法：ステップバイステップガイド"
    },
    {
      "id": "db55da3fc3",
      "title": "【完全解説】pandasでデータをフィルタリングする方法"
    },
    {
      "id": "814fd2e8e4",
      "title": "【完全保存版】pandasの基本的なデータ操作まとめ"
    },
    {
      "id": "aaf01d71b5",
      "title": "Pandasで欠損値を処理するテクニック：データクレンジングの基本"
    },
    {
      "id": "26d228663f",
      "title": "JavaScriptのconfirm関数の使い方を初心者向けに解説"
    },
    {
      "id": "fc72c98a6c",
      "title": "ウェブスクレイピングにおすすめのプログラミング言語とその使い方"
    },
    {
      "id": "a5abb1500b",
      "title": "JavaScriptのprompt関数でユーザー入力を取得する方法"
    },
    {
      "id": "612111a352",
      "title": "JavaScriptでカスタムダイアログを作成する方法（モーダルウィンドウ）を初心者向けに解説"
    },
    {
      "id": "fabf5b7fed",
      "title": "ウェブスクレイピングが禁止されているサイトを確認する方法と注意点"
    },
    { "id": "25dac95b8f", "title": "OpenPyXL応用編：条件付き書式とグラフ作成" },
    {
      "id": "99a0b871c9",
      "title": "OpenPyXLを使った実用的なスクリプト例＆効率的なデータ操作方法"
    },
    {
      "id": "9b15fed64e",
      "title": "Openpyxlのインストール方法：開発環境別ガイド"
    },
    {
      "id": "de5872c6bb",
      "title": "OpenPyXLによるExcelファイルの読み込みと書き込みの基本操作"
    },
    {
      "id": "37b7351017",
      "title": "OpenPyXLコマンド集：Excelファイルの読み込み・保存・書き換え・新規作成など"
    },
    {
      "id": "deeeb5df3f",
      "title": "無料でできる！Google Apps Scriptで業務を自動化する"
    },
    {
      "id": "600b4cdf20",
      "title": "PyScriptの一般的な概念と使い方のチュートリアル"
    },
    { "id": "03a3d955b8", "title": "Pandasのgroupbyを使いこなすためのガイド" },
    {
      "id": "2289b221b3",
      "title": "Pandas ilocで特定の行や列を抽出する方法を解説"
    },
    {
      "id": "023849c389",
      "title": "【完全解説】pandasで行・列を削除する様々な方法"
    },
    {
      "id": "7acc684a84",
      "title": "Matplotlibで目盛間隔を自在に設定【簡潔＆多彩な実用例】"
    },
    { "id": "8d23cf6c86", "title": "TynyDBでサクッとデータベースを使ってみた" },
    { "id": "8efbbe9bc1", "title": "アロー関数におけるThisの使い方" },
    {
      "id": "a4e987d175",
      "title": "matplotlibで日本語が文字化け！解決策を解説します"
    },
    {
      "id": "0bba869d7f",
      "title": "【savefig】matplotlibでグラフを保存する方法のバリエーション"
    },
    {
      "id": "d874e4e4a5",
      "title": "【JavaScript】値のない変数「undefined」について"
    },
    {
      "id": "38b83caefa",
      "title": "【JavaScript】toLocaleString()で地域に適したデータに変換する"
    },
    {
      "id": "226f76b55a",
      "title": "JavaScriptでコメントアウトをする２つの方法"
    },
    { "id": "48a1706eca", "title": "【JavaScript】for文の構文" },
    {
      "id": "983bd614bb",
      "title": "機械学習ライブラリ【scikit-learn】のインストール方法"
    },
    {
      "id": "9cfd3c755b",
      "title": "【JSON.stringify】JavaScriptオブジェクトをJSON文字列へ変換する強力なメソッド"
    },
    { "id": "6db6eb4af1", "title": "JavaScriptのfind関数について" },
    {
      "id": "09895de040",
      "title": "【 JavaScript】アロー関数で簡単に関数を記述する"
    },
    { "id": "1e68ed4e3d", "title": "JavaScriptにおける連想配列の実装" },
    { "id": "d7cdaa5ca0", "title": "JavaScriptで配列に追加する３つの方法" },
    {
      "id": "3635a91e3d",
      "title": "TypeScriptとは？〜JavaScriptと異なる静的型付け言語〜"
    },
    { "id": "f747870ae6", "title": "【JavaScrip】forEach()メソッドの使い方" },
    { "id": "7f0a22117f", "title": "JavaScriptのmap()関数の使い方" },
    {
      "id": "3a1dfb05d7",
      "title": "【完全保存版】JavaScriptのalert完全ガイド：使い方と応用テクニック"
    },
    {
      "id": "8acc23987b",
      "title": "Pythonのrequests | HTTPリクエストのライブラリ"
    },
    {
      "id": "011af72a91",
      "title": "【2024年】プログラミング言語ランキング｜TIOBE indexとGoogle検索数"
    },
    { "id": "768b84ef05", "title": "Pythonで四捨五入する4つの方法" },
    { "id": "7c252ab334", "title": "Pythonのバージョンを確認をする方法" },
    { "id": "9512d95d00", "title": "なぜHTMLはプログラミング言語ではないのか" },
    {
      "id": "9e6a72557a",
      "title": "Python コードのスタイルガイド【PEP8】とは？"
    },
    { "id": "27badc983d", "title": "Pythonのif文における複数条件の攻略" },
    {
      "id": "749fc650ca",
      "title": "【GAS】さまざまなトリガーを設定するScriptApp.newTrigger()について"
    },
    {
      "id": "d48ff4b2f6",
      "title": "Seabornを用いたヒストグラム（histplot）の作り方"
    },
    {
      "id": "dfe62e836a",
      "title": "Seabornを用いたペアプロット（paiaplot）の作り方"
    },
    {
      "id": "4621c1d55f",
      "title": "Seabornを用いた線グラフ（lineplot）の作り方"
    },
    {
      "id": "d80eae6e96",
      "title": "グラフ描画ライブラリSeabornを使ってみよう【Python】"
    },
    {
      "id": "f57e5cb1f4",
      "title": "Seabornを用いた散布図（scatterplot）の作り方"
    },
    {
      "id": "b8aed072d2",
      "title": "Seabornを用いた棒グラフ（barplot）の作り方"
    },
    {
      "id": "2c7d5490e6",
      "title": "Seabornによるヒートマップ(heatmap)の作り方"
    },
    {
      "id": "620c9c3321",
      "title": "Seabornを用いた箱ひげ図（boxplot）の作り方"
    },
    { "id": "1be0034108", "title": "Pythonにおけるelseの使い方3選" },
    {
      "id": "0f8ef3377b",
      "title": "【形態素解析】mecabをpythonで使用する方法"
    },
    {
      "id": "2ac878b0e2",
      "title": "PythonのPDF生成ライブラリ「reportlab」の使い方"
    },
    {
      "id": "b1556dea32",
      "title": "【Python】顔認識ライブラリ face_recognition の使い方"
    },
    { "id": "dbb1ded63b", "title": "【Python】三項演算子とは何か？" },
    {
      "id": "d6d824abba",
      "title": "Googleスプレッド シートで「スクリプトエディタ」が出 てこない時の対処法"
    },
    {
      "id": "8b940be7fb",
      "title": "GASを使ってGoogleスプレッドシートを検索する方法"
    },
    {
      "id": "37834f2f25",
      "title": "pipを使ってPythonライブラリをインストールする方法"
    },
    {
      "id": "48449a14a4",
      "title": "【Google】スプレッドシートからカレンダーにGASで自動的にイベントを組み込む方法"
    },
    { "id": "ad57366865", "title": "初心者でも書ける面白いPythonコード" },
    {
      "id": "96061e92f5",
      "title": "Google Apps Scriptでスプレッドシートのシートとセルを取得する関数一覧"
    },
    {
      "id": "d029fa3a95",
      "title": "Google Apps Script【GAS】によるGoogleフォームの扱い方入門"
    },
    { "id": "86e5014965", "title": "Pythonにおける配列の扱い方" },
    {
      "id": "e629fa6598",
      "title": "PythonでExcelを自在に操るための４つの方法"
    },
    {
      "id": "31489056e0",
      "title": "Google Apps ScriptでGoogle スプレッドシートを操る方法【業務自動化】"
    }
  ],
  "totalCount": 97,
  "offset": 0,
  "limit": 100
}
